git_wise/__init__.py
git_wise/cli.py
git_wise/config.py
git_wise/core/generator.py
git_wise/core/splitter.py
git_wise/models/git_models.py
git_wise/utils/console_utils.py
git_wise/utils/exceptions.py
git_wise/utils/git_utils.py
git_wise-0.1.4.dist-info/LICENSE
git_wise-0.1.4.dist-info/METADATA
git_wise-0.1.4.dist-info/WHEEL
git_wise-0.1.4.dist-info/entry_points.txt
git_wise-0.1.4.dist-info/top_level.txt
git_wise-0.1.4.dist-info/RECORD
