Metadata-Version: 2.1
Name: git-wise
Version: 0.1.4
Summary: AI-powered Git commit message generator
Author-email: creeponsky <creeponsky@gmail.com>
License: MIT License
Keywords: git,commit,AI,OpenAI
Classifier: License :: OSI Approved :: MIT License
Classifier: Programming Language :: Python
Classifier: Programming Language :: Python :: 3
Requires-Python: >=3.7
License-File: LICENSE
Requires-Dist: click >=8.0.0
Requires-Dist: rich >=13.9.0
Requires-Dist: gitpython >=3.1.0
Requires-Dist: openai >=1.52.0
Requires-Dist: pyyaml >=6.0.0
Requires-Dist: PyGithub >=2.0.0
Requires-Dist: questionary >=1.10.0
Requires-Dist: tiktoken >=0.5.0
Requires-Dist: pyperclip >=1.8.2
Provides-Extra: dev
Requires-Dist: pytest ; extra == 'dev'
Requires-Dist: pytest-cov ; extra == 'dev'
